aubio_beat_osc.py
aubio_beat_osc-1.2.dist-info/LICENSE
aubio_beat_osc-1.2.dist-info/METADATA
aubio_beat_osc-1.2.dist-info/WHEEL
aubio_beat_osc-1.2.dist-info/entry_points.txt
aubio_beat_osc-1.2.dist-info/top_level.txt
aubio_beat_osc-1.2.dist-info/RECORD
