Metadata-Version: 2.1
Name: aubio-beat-osc
Version: 1.2
Summary: Simple beat detection outputting to OSC servers
Home-page: UNKNOWN
Author: Lukas Jackowski
License: UNKNOWN
Project-URL: Source Code, https://github.com/DrLuke/aubio-beat-osc
Keywords: aubio beat detection osc
Platform: UNKNOWN
Requires-Dist: pyaudio
Requires-Dist: aubio
Requires-Dist: python-osc
Requires-Dist: numpy
